x4i3/__init__.py
x4i3/abundance.py
x4i3/endl_Z.py
x4i3/exfor_column_parsing.py
x4i3/exfor_dataset.py
x4i3/exfor_dicts.py
x4i3/exfor_entry.py
x4i3/exfor_exceptions.py
x4i3/exfor_field.py
x4i3/exfor_grammers.py
x4i3/exfor_manager.py
x4i3/exfor_particle.py
x4i3/exfor_reactions.py
x4i3/exfor_reference.py
x4i3/exfor_section.py
x4i3/exfor_subentry.py
x4i3/exfor_utilities.py
x4i3/pyparsing2.py
x4i3/pyparsing3.py
x4i3/data/README.data
x4i3/dicts/dict03.txt
x4i3/dicts/dict04.txt
x4i3/dicts/dict05.txt
x4i3/dicts/dict07.txt
x4i3/dicts/dict09.txt
x4i3/dicts/dict18.txt
x4i3/dicts/dict19.txt
x4i3/dicts/dict20.txt
x4i3/dicts/dict21.txt
x4i3/dicts/dict22.txt
x4i3/dicts/dict23.txt
x4i3/dicts/dict24.txt
x4i3/dicts/dict30.txt
x4i3/dicts/dict33.txt
x4i3/dicts/dict34.txt
x4i3/dicts/dict35.txt
x4i3/dicts/dict36.txt
x4i3/dicts/dict37.txt
x4i3/tests/12898.x4
x4i3/tests/E0783.x4
x4i3/tests/__init__.py
x4i3/tests/test_exfor_dataset.py
x4i3/tests/test_exfor_entry.py
x4i3/tests/test_exfor_fields.py
x4i3/tests/test_exfor_full_integration.py
x4i3/tests/test_exfor_manager.py
x4i3/tests/test_exfor_reaction.py
x4i3-1.2.4.dist-info/LICENSE.txt
x4i3-1.2.4.dist-info/METADATA
x4i3-1.2.4.dist-info/WHEEL
x4i3-1.2.4.dist-info/top_level.txt
x4i3-1.2.4.dist-info/RECORD
