Metadata-Version: 2.1
Name: x4i3
Version: 1.2.4
Summary: A "simple" python interface to the EXFOR library
Home-page: https://github.com/afedynitch/x4i3/
Author: David A. Brown (x4i3: Anatoli Fedynitch)
Author-email: dbrown@bnl.gov
Maintainer: Anatoli Fedynitch
Maintainer-email: afedynitch@gmail.com
Classifier: Programming Language :: Python
Classifier: Programming Language :: Python :: 3
Classifier: Programming Language :: Python :: 3.5
Classifier: Programming Language :: Python :: 3.6
Classifier: Programming Language :: Python :: 3.7
Classifier: Programming Language :: Python :: 3.8
Classifier: Programming Language :: Python :: 3.9
Classifier: Programming Language :: Python :: 3.10
Classifier: Topic :: Scientific/Engineering :: Physics
Classifier: Intended Audience :: Science/Research
Classifier: Development Status :: 4 - Beta
Classifier: License :: OSI Approved :: GNU General Public License v2 (GPLv2)
License-File: LICENSE.txt
Requires-Dist: tqdm
Requires-Dist: requests
Provides-Extra: tests
Requires-Dist: pytest ; extra == 'tests'
